vanilla/__init__.py
vanilla/model_views.py
vanilla/models.py
vanilla/tests.py
vanilla/views.py
django_vanilla_views-3.0.0.dist-info/LICENSE
django_vanilla_views-3.0.0.dist-info/METADATA
django_vanilla_views-3.0.0.dist-info/WHEEL
django_vanilla_views-3.0.0.dist-info/top_level.txt
django_vanilla_views-3.0.0.dist-info/RECORD
